asynciojobs/__init__.py
asynciojobs/bestset.py
asynciojobs/dotstyle.py
asynciojobs/job.py
asynciojobs/printjob.py
asynciojobs/purescheduler.py
asynciojobs/scheduler.py
asynciojobs/sequence.py
asynciojobs/version.py
asynciojobs/watch.py
asynciojobs/window.py
asynciojobs-0.21.3.dist-info/METADATA
asynciojobs-0.21.3.dist-info/WHEEL
asynciojobs-0.21.3.dist-info/licenses/LICENSE
asynciojobs-0.21.3.dist-info/RECORD
